empymod/__init__.py
empymod/__main__.py
empymod/filters.py
empymod/io.py
empymod/kernel.py
empymod/model.py
empymod/transform.py
empymod/utils.py
empymod/version.py
empymod/scripts/__init__.py
empymod/scripts/fdesign.py
empymod/scripts/tmtemod.py
empymod-2.6.0.dist-info/licenses/LICENSE
empymod-2.6.0.dist-info/licenses/NOTICE
empymod-2.6.0.dist-info/METADATA
empymod-2.6.0.dist-info/WHEEL
empymod-2.6.0.dist-info/entry_points.txt
empymod-2.6.0.dist-info/top_level.txt
empymod-2.6.0.dist-info/RECORD
