Metadata-Version: 2.4
Name: empymod
Version: 2.6.0
Summary: Open-source full 3D electromagnetic modeller for 1D VTI media
Author-email: The emsig community <info@emsig.xyz>
License: 
Project-URL: Homepage, https://emsig.xyz
Project-URL: Documentation, https://empymod.emsig.xyz
Project-URL: Repository, https://github.com/emsig/empymod
Classifier: Development Status :: 5 - Production/Stable
Classifier: License :: OSI Approved :: Apache Software License
Classifier: Programming Language :: Python
Requires-Python: >=3.11
License-File: LICENSE
License-File: NOTICE
Requires-Dist: numpy>=2.0.0
Requires-Dist: scipy
Requires-Dist: numba
Requires-Dist: libdlf
Requires-Dist: scooby
Provides-Extra: docs
Requires-Dist: ipympl; extra == "docs"
Requires-Dist: sphinx>=7.3; extra == "docs"
Requires-Dist: numpydoc; extra == "docs"
Requires-Dist: ipykernel; extra == "docs"
Requires-Dist: matplotlib; extra == "docs"
Requires-Dist: pickleshare; extra == "docs"
Requires-Dist: sphinx_design; extra == "docs"
Requires-Dist: sphinx_numfig; extra == "docs"
Requires-Dist: sphinx_gallery>=0.16; extra == "docs"
Requires-Dist: memory_profiler; extra == "docs"
Requires-Dist: sphinx_automodapi; extra == "docs"
Requires-Dist: pydata_sphinx_theme; extra == "docs"
Provides-Extra: tests
Requires-Dist: flake8; extra == "tests"
Requires-Dist: pytest; extra == "tests"
Requires-Dist: coveralls; extra == "tests"
Requires-Dist: pytest_cov; extra == "tests"
Requires-Dist: pytest_mpl; extra == "tests"
Requires-Dist: flake8-pyproject; extra == "tests"
Requires-Dist: pytest-console-scripts; extra == "tests"
Provides-Extra: all
Requires-Dist: empymod[docs]; extra == "all"
Requires-Dist: empymod[tests]; extra == "all"
Provides-Extra: build
Requires-Dist: setuptools_scm>=8; extra == "build"
Requires-Dist: setuptools>=64; extra == "build"
Dynamic: license-file
